{
  "title": "Docker swarm tutorial",
  "description": "Docker swarm essentials interactive tutorial",
  "difficulty": "Beginner",
  "time": "10-15 minutes",
  "details": {
    "steps": [
      {
        "title": "Creating a docker swarm cluster",
        "text": "step1.md"
      },
      {
        "title": "Scaling the docker swarm cluster",
        "text": "step2.md"
      },
      {
        "title": "Removing the docker swarm cluster",
        "text": "step3.md",
        "code": "script.sh"
      }
    ],
    "intro": {
      "text": "intro.md"
    },
    "finish": {
      "text": "finish.md"
    }
  },
  "environment": {
    "uilayout": "terminal"
  },
  "backend": {
    "imageid": "ubuntu:2004"
  }
}
